{
  "main": {
    "id": "8b8be3c4c8cde38e",
    "type": "split",
    "children": [
      {
        "id": "c2acda73e19fed06",
        "type": "tabs",
        "children": [
          {
            "id": "ba802ecedc187ccc",
            "type": "leaf",
            "state": {
              "type": "markdown",
              "state": {
                "file": "blog/2020/20180706_mitmproxy使用/index.md",
                "mode": "source",
                "source": true
              },
              "icon": "lucide-file",
              "title": "index"
            }
          },
          {
            "id": "a55dc14b93721b48",
            "type": "leaf",
            "state": {
              "type": "empty",
              "state": {},
              "icon": "lucide-file",
              "title": "New tab"
            }
          },
          {
            "id": "9871b5f642e29f40",
            "type": "leaf",
            "state": {
              "type": "markdown",
              "state": {
                "file": "about.md",
                "mode": "source",
                "source": true
              },
              "icon": "lucide-file",
              "title": "about"
            }
          }
        ]
      }
    ],
    "direction": "vertical"
  },
  "left": {
    "id": "642b333c0daf4ea7",
    "type": "split",
    "children": [
      {
        "id": "a68e63e1b66543dd",
        "type": "tabs",
        "children": [
          {
            "id": "4dc1ddf66f8bb832",
            "type": "leaf",
            "state": {
              "type": "file-explorer",
              "state": {
                "sortOrder": "alphabetical"
              },
              "icon": "lucide-folder-closed",
              "title": "Files"
            }
          },
          {
            "id": "d2f877315c116b6a",
            "type": "leaf",
            "state": {
              "type": "search",
              "state": {
                "query": "",
                "matchingCase": false,
                "explainSearch": false,
                "collapseAll": false,
                "extraContext": false,
                "sortOrder": "alphabetical"
              },
              "icon": "lucide-search",
              "title": "Search"
            }
          },
          {
            "id": "55a0ed63e0bb5bf6",
            "type": "leaf",
            "state": {
              "type": "bookmarks",
              "state": {},
              "icon": "lucide-bookmark",
              "title": "Bookmarks"
            }
          }
        ]
      }
    ],
    "direction": "horizontal",
    "width": 354.5
  },
  "right": {
    "id": "8d000694e1bb185b",
    "type": "split",
    "children": [
      {
        "id": "4f994f0b841a6577",
        "type": "tabs",
        "children": [
          {
            "id": "1045e3f569bf5afc",
            "type": "leaf",
            "state": {
              "type": "backlink",
              "state": {
                "file": "blog/2024/08-25 hugo 博客本地编辑提效/index.md",
                "collapseAll": false,
                "extraContext": false,
                "sortOrder": "alphabetical",
                "showSearch": false,
                "searchQuery": "",
                "backlinkCollapsed": false,
                "unlinkedCollapsed": true
              },
              "icon": "links-coming-in",
              "title": "Backlinks for index"
            }
          },
          {
            "id": "3a24237967310cbd",
            "type": "leaf",
            "state": {
              "type": "outgoing-link",
              "state": {
                "file": "blog/2024/寸剑/index.md",
                "linksCollapsed": false,
                "unlinkedCollapsed": true
              },
              "icon": "links-going-out",
              "title": "Outgoing links from index"
            }
          },
          {
            "id": "ad7ec95ebdb7e510",
            "type": "leaf",
            "state": {
              "type": "tag",
              "state": {
                "sortOrder": "frequency",
                "useHierarchy": true
              },
              "icon": "lucide-tags",
              "title": "Tags"
            }
          },
          {
            "id": "78385f96f77f2e42",
            "type": "leaf",
            "state": {
              "type": "outline",
              "state": {
                "file": "blog/2024/寸剑/index.md"
              },
              "icon": "lucide-list",
              "title": "Outline of index"
            }
          }
        ]
      }
    ],
    "direction": "horizontal",
    "width": 300,
    "collapsed": true
  },
  "left-ribbon": {
    "hiddenItems": {
      "switcher:Open quick switcher": false,
      "graph:Open graph view": false,
      "templates:Insert template": false,
      "command-palette:Open command palette": false,
      "obsidian-excalidraw-plugin:Create new drawing": false,
      "table-editor-obsidian:Advanced Tables Toolbar": false
    }
  },
  "active": "4dc1ddf66f8bb832",
  "lastOpenFiles": [
    "blog/2020/20180706_mitmproxy使用",
    "blog/2018/08-11-Golang下的Error.md",
    "blog/2018/09-03-sync.Once.md",
    "blog/2018/12-29-How to use godog.md",
    "blog/2018/12-09-Net Transport.md",
    "blog/2018/11-20-NSS初窥.md",
    "blog/2018/07-28-Tcp Server Design.md",
    "blog/2018/03-31-包管理.md",
    "blog/2024/12-29 辅助编程应用/index.md",
    "blog/2024/rust 异步/index.md",
    "about.md",
    "blog/2024/08-25 hugo 博客本地编辑提效/index.md",
    "blog/2024/12-29 辅助编程应用/Untitled",
    "blog/2024/12-29 辅助编程应用",
    "blog/2024/使用模板创建一篇博客/images/placehold.png",
    "blog/2024/使用模板创建一篇博客/index.md",
    "blog/2024/使用模板创建一篇博客/images",
    "blog/2024/使用模板创建一篇博客",
    "blog/2024/08-25 hugo 博客本地编辑提效/images/image-md.png",
    "blog/2024/hugo11111/images/placehold.png",
    "blog/2024/hugo11111/index.md",
    "blog/2024/hugo11111/images",
    "blog/2024/hugo11111",
    "blog/2024/08-25 hugo 博客本地编辑提效/images/page-bundle.png",
    "blog/2024/hugo使用模板/index.md",
    "blog/2024/08-25 hugo 博客本地编辑提效/images/hugo-commit.png",
    "blog/2024/08-25 hugo 博客本地编辑提效/images/public-dir.png",
    "blog/2024/08-25 hugo 博客本地编辑提效/images/public-dir.png",
    "blog/2024/08-25 hugo 博客本地编辑提效/images/hugo-dir.png",
    "blog/2024/08-25 hugo 博客本地编辑提效/images/repo-branch.png",
    "blog/2024/寸剑/index.md",
    "blog/2023/01. go 中 string 并发写导致的 panic/index.md",
    "blog/2024/11-14 github ssh-agent 配置/index.md",
    "blog/2024/11-14 github ssh-agent 配置/s2.png",
    "blog/2024/08-25 hugo 博客本地编辑提效/images",
    "blog/2024/rust gui 设计/index.md",
    "blog/2024/discordgo/index.md",
    "blog/2024/数据统计/index.md",
    "blog/2024/Untitled.md",
    "blog/2024/11-14 github ssh-agent 配置/images",
    "blog/2024/rust 模块/index.md",
    "blog/2024/hugo使用模板",
    "greatperson/2022.03.12. 认真地看待炒股.md",
    "blog/2024/rust option/index.md",
    "blog/2024/08-25 hugo 博客本地编辑提效",
    "blog/_index.md"
  ]
}